nlgm/__init__.py
nlgm/autoencoder.py
nlgm/manifolds.py
nlgm/optimizers.py
nlgm/searchspace.py
nlgm/train.py
nlgm/visualize.py
neural_geometry-0.1.2.dist-info/LICENSE
neural_geometry-0.1.2.dist-info/METADATA
neural_geometry-0.1.2.dist-info/WHEEL
neural_geometry-0.1.2.dist-info/top_level.txt
neural_geometry-0.1.2.dist-info/RECORD
