Metadata-Version: 2.1
Name: neural-geometry
Version: 0.1.2
Summary: Latent Space Geometry for Neural Networks in Python
Author-email: Anupam Bhakta <ab5494@columbia.edu>, Adam Mehdi <adm2243@columbia.edu>, Kevin Qiu <kzq2000@columbia.edu>
License: MIT License
Project-URL: Homepage, https://github.com/ae-bii/neural-geometry
Project-URL: Documentation, https://ae-bii.github.io/neural-geometry/
Project-URL: Release notes, https://github.com/ae-bii/neural-geometry/releases
Project-URL: Issues, https://github.com/ae-bii/neural-geometry/issues
Classifier: Development Status :: 3 - Alpha
Classifier: Intended Audience :: Developers
Classifier: Intended Audience :: Science/Research
Classifier: License :: OSI Approved :: MIT License
Classifier: Operating System :: OS Independent
Classifier: Programming Language :: Python :: 3
Classifier: Topic :: Scientific/Engineering :: Artificial Intelligence
Classifier: Topic :: Scientific/Engineering :: Mathematics
Classifier: Topic :: Software Development :: Libraries
Requires-Python: >=3.8
License-File: LICENSE
Requires-Dist: torch
Requires-Dist: numpy
Requires-Dist: tqdm
Provides-Extra: dev
Requires-Dist: pytest ; extra == 'dev'
Requires-Dist: tox ; extra == 'dev'
Requires-Dist: tox-uv ; extra == 'dev'
Requires-Dist: pre-commit ; extra == 'dev'
Provides-Extra: vis
Requires-Dist: matplotlib ; extra == 'vis'
Requires-Dist: networkx ; extra == 'vis'
